_pinpointPy.cp313-win_amd64.pyd
pinpointPy/Common.py
pinpointPy/CommonPlugin.py
pinpointPy/Defines.py
pinpointPy/Helper.py
pinpointPy/Interceptor.py
pinpointPy/RequestPlugins.py
pinpointPy/TraceContext.py
pinpointPy/WSGIPlugin.py
pinpointPy/__init__.py
pinpointPy/pinpoint.py
pinpointPy/Bottle/RequestPlugin.py
pinpointPy/Bottle/__init__.py
pinpointPy/Django/BaseDjangoRequestPlugins.py
pinpointPy/Django/DjangoMiddleWare.py
pinpointPy/Django/__init__.py
pinpointPy/Fastapi/AsyCommon.py
pinpointPy/Fastapi/AsyCommonPlugin.py
pinpointPy/Fastapi/AsyRequestPlugin.py
pinpointPy/Fastapi/FastAPIRequestPlugin.py
pinpointPy/Fastapi/PinTranscation.py
pinpointPy/Fastapi/__init__.py
pinpointPy/Fastapi/middleware.py
pinpointPy/Fastapi/test_fastapi.py
pinpointPy/Fastapi/_aioredis/AioRedisPlugins.py
pinpointPy/Fastapi/_aioredis/__init__.py
pinpointPy/Fastapi/_httpx/__init__.py
pinpointPy/Fastapi/_httpx/httpxPlugins.py
pinpointPy/Flask/FlaskPlugins.py
pinpointPy/Flask/PinPointMiddleWare.py
pinpointPy/Flask/__init__.py
pinpointPy/Flask/test_case.py
pinpointPy/grpc_/GrpcRequestPlugins.py
pinpointPy/grpc_/__init__.py
pinpointPy/libs/__init__.py
pinpointPy/libs/_MySQLdb/BaseCursorPlugins.py
pinpointPy/libs/_MySQLdb/MySQLdbPlugin.py
pinpointPy/libs/_MySQLdb/__init__.py
pinpointPy/libs/_MySQLdb/test_case.py
pinpointPy/libs/_MysqlConnector/CMysqlPlugin.py
pinpointPy/libs/_MysqlConnector/MysqlPlugin.py
pinpointPy/libs/_MysqlConnector/__init__.py
pinpointPy/libs/_MysqlConnector/test_case.py
pinpointPy/libs/_PyMysql/PyMysqlPlugin.py
pinpointPy/libs/_PyMysql/__init__.py
pinpointPy/libs/_PyMysql/test_case.py
pinpointPy/libs/_asyncio/__init__.py
pinpointPy/libs/_asyncio/test_case.py
pinpointPy/libs/_celery/__init__.py
pinpointPy/libs/_kombu/KombuPlugin.py
pinpointPy/libs/_kombu/__init__.py
pinpointPy/libs/_kombu/test_case.py
pinpointPy/libs/_process/__init__.py
pinpointPy/libs/_psycopg2/PsycopgPlugins.py
pinpointPy/libs/_psycopg2/__init__.py
pinpointPy/libs/_psycopg2/test_case.py
pinpointPy-1.4.1.dist-info/LICENSE
pinpointPy-1.4.1.dist-info/METADATA
pinpointPy-1.4.1.dist-info/NOTICE
pinpointPy-1.4.1.dist-info/WHEEL
pinpointPy-1.4.1.dist-info/top_level.txt
pinpointPy-1.4.1.dist-info/RECORD
