Metadata-Version: 2.1
Name: pinpointPy
Version: 1.4.1
Summary: The pinpoint Python library
Home-page: https://github.com/pinpoint-apm/pinpoint-c-agent
Author: pinpoint members
Author-email: cd_pinpoint members <dl_cd_pinpoint@navercorp.com>
License: Apache License 2.0
Project-URL: Bug Tracker, https://github.com/pinpoint-apm/pinpoint-c-agentissues
Project-URL: Documentation, https://github.com/pinpoint-apm/pinpoint-c-agent/tree/dev/DOC/PY
Project-URL: Source Code, https://github.com/pinpoint-apm/pinpoint-c-agent
Keywords: pinpoint
Classifier: Operating System :: OS Independent
Classifier: Programming Language :: Python :: 2.7
Classifier: Programming Language :: Python :: 3.7
Classifier: Programming Language :: Python :: 3.8
Classifier: Programming Language :: Python :: 3.9
Classifier: Programming Language :: Python :: 3.10
Classifier: Programming Language :: Python :: 3.11
Classifier: Programming Language :: Python :: 3.12
Classifier: Programming Language :: Python :: Implementation :: CPython
Classifier: Programming Language :: Python :: Implementation :: PyPy
Requires-Python: !=3.0.*,!=3.1.*,!=3.2.*,!=3.3.*,!=3.4.*,!=3.5.*,!=3.6.*,>=2.7
License-File: LICENSE
License-File: NOTICE
